transfer_unit.v
module transfer_unit (
    input wire [31:0] A,
    input wire [31:0] B,
    input wire sel,
    output wire [31:0] Y

);

assign Y = sel ? B : A;
    
endmodule

multipler.v
module multipler (
    input wire [31:0] A,
    input wire [31:0] B,
    output wire [31:0] Y
);
assign Y = A * B ;

    
endmodule

shifter_unit.v
module shifter_unit (
        input wire [31:0] A,
        input wire shift,
        output wire [31:0] Y


);

assign Y = (shift) ? A>>1 : A<<1;
endmodule

logical_unit.v
module logical_unit (
    input wire [31:0] A,
    input wire [31:0] B,
    input wire [1:0] sel,
    output reg [31:0] Y
    
);

always @(*)
    begin
        case (sel)
           2'b00 : Y = ( A & B);
           2'b01 : Y = ( A | B);
           2'b10 : Y = (A ^ B);
           2'b11 : Y = ~A; 
            default: Y = 0;
        endcase
    end

    
endmodule

arthimatic_unit.v
module arthimatic_unit (
    input wire [31:0] A,
    input wire [31:0] B,
    input wire sub,
    output wire [32:0] Y
);
wire [31:0] B_xor;
assign B_xor = B ^ {32{sub}};

assign Y = A + B_xor + sub;

    
endmodule

data_path.v
module datapath (
    input wire [31:0] A,
    input wire [31:0] B,

    input wire arithmic_op,
    input wire sub,
    input wire logic_op,
    input wire [1:0] sel,
    input wire shift_op,
    input wire shift_right,
    input wire mul_op,
    input wire trans_op,
    input wire trans_sel,

    output reg [31:0] Y,
    output wire carry
);
    wire [32:0] arith_out;
    wire [31:0] logic_out,shift_out,mul_out,trans_out;


    arthimatic_unit  AU (A,B,sub,arith_out);
    logical_unit  LU (A,B,sel,logic_out);
    shifter_unit SU (A,shift_right,shift_out);
    multipler MU (A,B,mul_out);
    transfer_unit TU (A,B,trans_sel,trans_out);

    assign carry = arith_out[32];

    always @(*)
    begin
        if (arithmic_op) Y = arith_out[31:0];
        else if (logic_op) Y = logic_out;
        else if (shift_op) Y = shift_out;
        else if (mul_op) Y = mul_out;
        else if (trans_op) Y = trans_out;
        else Y = 0;
    end 

    
endmodule

controller.v
module controller(
    input wire [3:0] op,

    output reg arithmic_op,
    output reg sub,
    output reg logic_op,
    output reg [1:0] sel,
    output reg shift_op,
    output reg shift_right,
    output reg mul_op,
    output reg trans_op,
    output reg trans_sel
);

always @(*)
begin 
    arithmic_op = 0;sub = 0;
    logic_op = 0; sel = 0;
    shift_op = 0; shift_right = 0;
    mul_op = 0; trans_op = 0;
    trans_sel = 0;
    
    case (op)
    4'd0   : begin arithmic_op = 1; sub = 0; end // ADD
    4'd1 : begin arithmic_op = 1; sub = 1; end // SUB

    4'd2 : begin logic_op = 1; sel = 2'b00 ; end // AND
    4'd3 : begin logic_op = 1; sel = 2'b01 ; end // OR
    4'd4 : begin logic_op = 1; sel = 2'b10 ; end // XOR
    4'd5 : begin logic_op = 1; sel = 2'b11 ; end // NOT

    4'd6 : begin shift_op = 1; shift_right = 0; end // LEFT_SHIFT
    4'd7 : begin shift_op = 1; shift_right = 1; end // RIGHT_SHIFT

    4'd8 : begin mul_op = 1; end // MUL

    4'd9 : begin trans_op = 1; trans_sel = 0; end // MOV A
    4'd10 : begin trans_op = 1; trans_sel = 1; end // MOV B
        
    endcase


end
endmodule

top_alu.v
module top_alu (
    input  wire [31:0] A,
    input  wire [31:0] B,
    input  wire [3:0]  op,
    output wire [31:0] Y,
    output wire        carry
);

    wire arithmetic_op, sub, logic_op, shift_op, shift_right;
    wire mul_op, trans_op, trans_sel;
    wire [1:0] sel;

    controller CTRL (
        .op(op),
        .arithmic_op(arithmetic_op),
        .sub(sub),
        .logic_op(logic_op),
        .sel(sel),
        .shift_op(shift_op),
        .shift_right(shift_right),
        .mul_op(mul_op),
        .trans_op(trans_op),
        .trans_sel(trans_sel)
    );

    datapath DP (
        .A(A), .B(B),
        .arithmic_op(arithmetic_op),
        .sub(sub),
        .logic_op(logic_op),
        .sel(sel),
        .shift_op(shift_op),
        .shift_right(shift_right),
        .mul_op(mul_op),
        .trans_op(trans_op),
        .trans_sel(trans_sel),
        .Y(Y),
        .carry(carry)
    );

endmodule

32_bitTB.v
module tb_32_bit;


reg [31:0] A,B;
reg [3:0] op;
wire [31:0] Y;
wire carry;

top_alu DUT (A,B,op,Y,carry);

initial begin
    A = 32'd56; B = 32'd32;

 $dumpfile("alu.vcd");
        $dumpvars(0, tb_32_bit);

    #10    op = 4'd0;  // ADD
     #10    op = 4'd1;  // SUB
     #10    op = 4'd2;  // AND
     #10    op = 4'd3;  // OR
     #10    op = 4'd4;  // XOR
     #10    op = 4'd5;  // NOT
     #10    op = 4'd6;  // LSHIFT
     #10    op = 4'd7;  // RSHIFT
     #10    op = 4'd8;  // MUL
     #10    op = 4'd9;  // MOV A
     #10    op = 4'd10; // MOV B
     $finish;
end


endmodule

alu.vcd
$date
	Fri Jan 30 22:49:02 2026
$end
$version
	Icarus Verilog
$end
$timescale
	1s
$end
$scope module tb_32_bit $end
$var wire 1 ! carry $end
$var wire 32 " Y [31:0] $end
$var reg 32 # A [31:0] $end
$var reg 32 $ B [31:0] $end
$var reg 4 % op [3:0] $end
$scope module DUT $end
$var wire 32 & A [31:0] $end
$var wire 32 ' B [31:0] $end
$var wire 4 ( op [3:0] $end
$var wire 1 ) trans_sel $end
$var wire 1 * trans_op $end
$var wire 1 + sub $end
$var wire 1 , shift_right $end
$var wire 1 - shift_op $end
$var wire 2 . sel [1:0] $end
$var wire 1 / mul_op $end
$var wire 1 0 logic_op $end
$var wire 1 ! carry $end
$var wire 1 1 arithmetic_op $end
$var wire 32 2 Y [31:0] $end
$scope module CTRL $end
$var wire 4 3 op [3:0] $end
$var reg 1 1 arithmic_op $end
$var reg 1 0 logic_op $end
$var reg 1 / mul_op $end
$var reg 2 4 sel [1:0] $end
$var reg 1 - shift_op $end
$var reg 1 , shift_right $end
$var reg 1 + sub $end
$var reg 1 * trans_op $end
$var reg 1 ) trans_sel $end
$upscope $end
$scope module DP $end
$var wire 32 5 A [31:0] $end
$var wire 32 6 B [31:0] $end
$var wire 1 1 arithmic_op $end
$var wire 1 0 logic_op $end
$var wire 1 / mul_op $end
$var wire 2 7 sel [1:0] $end
$var wire 1 - shift_op $end
$var wire 1 , shift_right $end
$var wire 1 + sub $end
$var wire 1 * trans_op $end
$var wire 1 ) trans_sel $end
$var wire 32 8 trans_out [31:0] $end
$var wire 32 9 shift_out [31:0] $end
$var wire 32 : mul_out [31:0] $end
$var wire 32 ; logic_out [31:0] $end
$var wire 1 ! carry $end
$var wire 33 < arith_out [32:0] $end
$var reg 32 = Y [31:0] $end
$scope module AU $end
$var wire 32 > A [31:0] $end
$var wire 32 ? B [31:0] $end
$var wire 32 @ B_xor [31:0] $end
$var wire 1 + sub $end
$var wire 33 A Y [32:0] $end
$upscope $end
$scope module LU $end
$var wire 32 B A [31:0] $end
$var wire 32 C B [31:0] $end
$var wire 2 D sel [1:0] $end
$var reg 32 E Y [31:0] $end
$upscope $end
$scope module MU $end
$var wire 32 F A [31:0] $end
$var wire 32 G B [31:0] $end
$var wire 32 H Y [31:0] $end
$upscope $end
$scope module SU $end
$var wire 32 I A [31:0] $end
$var wire 1 , shift $end
$var wire 32 J Y [31:0] $end
$upscope $end
$scope module TU $end
$var wire 32 K A [31:0] $end
$var wire 32 L B [31:0] $end
$var wire 1 ) sel $end
$var wire 32 M Y [31:0] $end
$upscope $end
$upscope $end
$upscope $end
$upscope $end
$enddefinitions $end
$comment Show the parameter values. $end
$dumpall
$end
#0
$dumpvars
b1xx000 M
b100000 L
b111000 K
b0xx1xx00 J
b111000 I
b11100000000 H
b100000 G
b111000 F
b0 E
bx D
b100000 C
b111000 B
bx A
bx @
b100000 ?
b111000 >
b0 =
bx <
b0 ;
b11100000000 :
b0xx1xx00 9
b1xx000 8
bx 7
b100000 6
b111000 5
bx 4
bx 3
b0 2
x1
x0
x/
bx .
x-
x,
x+
x*
x)
bx (
b100000 '
b111000 &
bx %
b100000 $
b111000 #
b0 "
x!
$end
#10
0!
b111000 8
b111000 M
b1110000 9
b1110000 J
b100000 ;
b100000 E
b1011000 <
b1011000 A
b100000 @
b1011000 "
b1011000 2
b1011000 =
0)
0*
0/
0,
0-
b0 .
b0 4
b0 7
b0 D
00
0+
11
b0 %
b0 (
b0 3
#20
1!
b11111111111111111111111111011111 @
b11000 "
b11000 2
b11000 =
b100000000000000000000000000011000 <
b100000000000000000000000000011000 A
1+
11
b1 %
b1 (
b1 3
#30
0!
b100000 @
b100000 "
b100000 2
b100000 =
10
b1011000 <
b1011000 A
0+
01
b10 %
b10 (
b10 3
#40
b111000 "
b111000 2
b111000 =
b111000 ;
b111000 E
b1 .
b1 4
b1 7
b1 D
10
b11 %
b11 (
b11 3
#50
b11000 "
b11000 2
b11000 =
b11000 ;
b11000 E
b10 .
b10 4
b10 7
b10 D
10
b100 %
b100 (
b100 3
#60
b11111111111111111111111111000111 "
b11111111111111111111111111000111 2
b11111111111111111111111111000111 =
b11111111111111111111111111000111 ;
b11111111111111111111111111000111 E
b11 .
b11 4
b11 7
b11 D
10
b101 %
b101 (
b101 3
#70
b100000 ;
b100000 E
b1110000 "
b1110000 2
b1110000 =
1-
b0 .
b0 4
b0 7
b0 D
00
b110 %
b110 (
b110 3
#80
b11100 "
b11100 2
b11100 =
b11100 9
b11100 J
1,
1-
b111 %
b111 (
b111 3
#90
b1110000 9
b1110000 J
b11100000000 "
b11100000000 2
b11100000000 =
1/
0,
0-
b1000 %
b1000 (
b1000 3
#100
b111000 "
b111000 2
b111000 =
1*
0/
b1001 %
b1001 (
b1001 3
#110
b100000 "
b100000 2
b100000 =
b100000 8
b100000 M
1)
1*
b1010 %
b1010 (
b1010 3
